django_app_parameter/__init__.py
django_app_parameter/admin.py
django_app_parameter/apps.py
django_app_parameter/constants.py
django_app_parameter/context_processors.py
django_app_parameter/data_for_test.json
django_app_parameter/forms.py
django_app_parameter/management/__init__.py
django_app_parameter/management/commands/__init__.py
django_app_parameter/management/commands/dap_dump.py
django_app_parameter/management/commands/dap_load.py
django_app_parameter/management/commands/dap_rotate_key.py
django_app_parameter/managers.py
django_app_parameter/migrations/0001_initial.py
django_app_parameter/migrations/0002_parameter_is_global_alter_parameter_description_and_more.py
django_app_parameter/migrations/0003_alter_parameter_value_type.py
django_app_parameter/migrations/0004_add_new_parameter_types.py
django_app_parameter/migrations/0005_parametervalidator.py
django_app_parameter/migrations/0006_parameter_enable_cypher.py
django_app_parameter/migrations/0007_parameter_enable_history_parameterhistory.py
django_app_parameter/migrations/0008_parameterbool_parameterdate_parameterdatetime_and_more.py
django_app_parameter/migrations/0009_alter_parameter_value_alter_parameterhistory_value.py
django_app_parameter/migrations/__init__.py
django_app_parameter/models.py
django_app_parameter/templates/admin/django_app_parameter/parameter/change_form.html
django_app_parameter/utils.py
django_app_parameter-3.2.0.dist-info/METADATA
django_app_parameter-3.2.0.dist-info/WHEEL
django_app_parameter-3.2.0.dist-info/licenses/LICENSE
django_app_parameter-3.2.0.dist-info/RECORD
