Metadata-Version: 2.4
Name: django-app-parameter
Version: 3.2.0
Summary: App-Parameter is a very simple Django app to save application's parameter in the database.
License: CC0 1.0 Universal
License-File: LICENSE
Keywords: Django,Parameter,Configuration
Author: Swann
Author-email: swann.bouviermuller@gmail.com
Maintainer: Swann
Maintainer-email: swann.bouviermuller@gmail.com
Requires-Python: >=3.10,<4.0
Classifier: Development Status :: 5 - Production/Stable
Classifier: Environment :: Web Environment
Classifier: Framework :: Django
Classifier: Framework :: Django :: 4.2
Classifier: Framework :: Django :: 5.2
Classifier: Framework :: Django :: 6.0
Classifier: Intended Audience :: Developers
Classifier: License :: CC0 1.0 Universal (CC0 1.0) Public Domain Dedication
Classifier: License :: Other/Proprietary License
Classifier: Operating System :: OS Independent
Classifier: Programming Language :: Python
Classifier: Programming Language :: Python :: 3
Classifier: Programming Language :: Python :: 3.10
Classifier: Programming Language :: Python :: 3.11
Classifier: Programming Language :: Python :: 3.12
Classifier: Programming Language :: Python :: 3.13
Classifier: Programming Language :: Python :: 3.14
Classifier: Topic :: Software Development :: Libraries :: Python Modules
Provides-Extra: cryptography
Requires-Dist: Django (>=4.2,<7.0)
Project-URL: Bug Tracker, https://github.com/Swannbm/django-app-parameter/issues
Project-URL: Documentation, https://django-app-parameter.readthedocs.io/
Project-URL: Homepage, https://github.com/Swannbm/django-app-parameter
Project-URL: Repository, https://github.com/Swannbm/django-app-parameter
